contact_phone_local/__init__.py
contact_phone_local/contact_phone_local.py
contact_phone_local/contact_phone_local_constants.py
contact_phone_local-0.0.26.dist-info/METADATA
contact_phone_local-0.0.26.dist-info/WHEEL
contact_phone_local-0.0.26.dist-info/top_level.txt
contact_phone_local-0.0.26.dist-info/RECORD
