Metadata-Version: 2.1
Name: contact-phone-local
Version: 0.0.26
Summary: PyPI Package for Circles contact-phone-local Python
Home-page: https://github.com/circles-zone/contact-phone-local-python-package
Author: Circles
Author-email: info@circlez.ai
Classifier: Programming Language :: Python :: 3
Classifier: License :: Other/Proprietary License
Classifier: Operating System :: OS Independent
Requires-Dist: database-mysql-local >=0.0.290
Requires-Dist: logger-local >=0.0.135
Requires-Dist: phones-local >=0.0.23
